girepo/__init__.py
girepo/arg_parser.py
girepo/extractor.py
girepo/fetch.py
girepo/formatter.py
girepo/grprint.py
girepo/sort.py
girepo-0.3.2.dist-info/LICENSE
girepo-0.3.2.dist-info/METADATA
girepo-0.3.2.dist-info/WHEEL
girepo-0.3.2.dist-info/entry_points.txt
girepo-0.3.2.dist-info/top_level.txt
girepo-0.3.2.dist-info/RECORD
