Metadata-Version: 2.1
Name: girepo
Version: 0.3.2
Summary: A tool for printing github repository information as a markdown table format.
Home-page: https://github.com/ta08/girepo
Author: ta08
Author-email: marl4dev@gmail.com
License: "Apache License 2.0"
Platform: UNKNOWN
Classifier: Development Status :: 3 - Alpha
Classifier: License :: OSI Approved :: Apache Software License
Classifier: Topic :: Documentation
Classifier: Programming Language :: Python
Classifier: Programming Language :: Python :: 3.5
Classifier: Programming Language :: Python :: 3.6
Classifier: Programming Language :: Python :: 3.7
Classifier: Programming Language :: Python :: 3.8
Requires-Python: >=3.5
Requires-Dist: requests
